{"stats":{"minecraft:picked_up":{"minecraft:shroomlight":1,"minecraft:white_concrete":17,"minecraft:mossy_stone_bricks":24,"minecraft:dirt":4},"minecraft:custom":{"minecraft:time_since_rest":76449,"minecraft:crouch_one_cm":2189,"minecraft:sprint_one_cm":2682,"minecraft:play_time":76449,"minecraft:damage_taken":20,"minecraft:walk_one_cm":156669,"minecraft:sneak_time":1447,"minecraft:walk_under_water_one_cm":3842,"minecraft:jump":169,"minecraft:leave_game":3,"minecraft:walk_on_water_one_cm":2538,"minecraft:time_since_death":76449,"minecraft:climb_one_cm":2,"minecraft:total_world_time":76449,"minecraft:fly_one_cm":283521},"minecraft:used":{"minecraft:calcite":5,"minecraft:shroomlight":1,"minecraft:smooth_basalt":1,"minecraft:smooth_quartz_stairs":11,"minecraft:birch_planks":27,"minecraft:red_stained_glass":89,"minecraft:smooth_sandstone":4,"minecraft:red_nether_bricks":1,"minecraft:quartz_block":5,"minecraft:smooth_quartz":27,"minecraft:polished_diorite":2}},"DataVersion":3218}